setup.py
audiotools.egg-info/PKG-INFO
audiotools.egg-info/SOURCES.txt
audiotools.egg-info/dependency_links.txt
audiotools.egg-info/requires.txt
audiotools.egg-info/top_level.txt
pyAudioAnalysis/__init__.py
pyAudioAnalysis/analyzeMovieSound.py
pyAudioAnalysis/audioAnalysis.py
pyAudioAnalysis/audioAnalysisRecordAlsa.py
pyAudioAnalysis/audioBasicIO.py
pyAudioAnalysis/audioFeatureExtraction.py
pyAudioAnalysis/audioSegmentation.py
pyAudioAnalysis/audioTrainTest.py
pyAudioAnalysis/audioVisualization.py
pyAudioAnalysis/convertToWav.py
pyAudioAnalysis/utilities.py