Metadata-Version: 1.1
Name: audiotools
Version: 0.1.0
Summary: Python Audio Analysis Library: Feature Extraction, Classification, Segmentation and Applications
Home-page: https://github.com/tyiannak/pyAudioAnalysis
Author: Theodoros Giannakopoulos
Author-email: tyiannak@gmail.com
License: Apache 2.0
Keywords: audio analysis feature extraction classification segmentation visualization
Platform: UNKNOWN
Classifier: Development Status :: 5 - Production/Stable
Classifier: Intended Audience :: Developers
Classifier: Topic :: Multimedia :: Sound/Audio :: Analysis
Classifier: License :: OSI Approved :: Apache Software License
Classifier: Programming Language :: Python :: 2
Classifier: Programming Language :: Python :: 2.7
